odoo/addons/connector_importer_demo/__init__.py
odoo/addons/connector_importer_demo/__manifest__.py
odoo/addons/connector_importer_demo/hooks.py
odoo/addons/connector_importer_demo/data/import_backend.xml
odoo/addons/connector_importer_demo/data/import_recordset.xml
odoo/addons/connector_importer_demo/data/import_source.xml
odoo/addons/connector_importer_demo/data/import_type.xml
odoo/addons/connector_importer_demo/example/res.partner.csv
odoo/addons/connector_importer_demo/static/description/icon.png
odoo12_addon_connector_importer_demo-12.0.1.0.0.99.dev1.dist-info/METADATA
odoo12_addon_connector_importer_demo-12.0.1.0.0.99.dev1.dist-info/WHEEL
odoo12_addon_connector_importer_demo-12.0.1.0.0.99.dev1.dist-info/top_level.txt
odoo12_addon_connector_importer_demo-12.0.1.0.0.99.dev1.dist-info/RECORD
